pyrdt/__init__.py
pyrdt/atom.py
pyrdt/combo.py
pyrdt/math.py
pyrdt/stat.py
wfzdy_pyrdt/__init__.py
wfzdy_pyrdt/atom.py
wfzdy_pyrdt/combo.py
wfzdy_pyrdt/math.py
wfzdy_pyrdt/stat.py
wfzdy_pyrdt-1.0.1.dist-info/LICENSE
wfzdy_pyrdt-1.0.1.dist-info/METADATA
wfzdy_pyrdt-1.0.1.dist-info/WHEEL
wfzdy_pyrdt-1.0.1.dist-info/top_level.txt
wfzdy_pyrdt-1.0.1.dist-info/RECORD
