Metadata-Version: 2.1
Name: wfzdy-pyrdt
Version: 1.0.1
Summary: reshape data type in py language 
Home-page: http://www.reshapedata.com
Author: Reshapedata
Author-email: hulilei@takewiki.com.cn
License: dingyan
Keywords: reshapedata,rdt,wfzdy_pyrdt
Platform: UNKNOWN
Requires-Python: >=3.6
License-File: LICENSE
Requires-Dist: requests
